dravik/__init__.py
dravik/__main__.py
dravik/app.py
dravik/hledger.py
dravik/models.py
dravik/services.py
dravik/utils.py
dravik/validators.py
dravik/widgets.py
dravik/screens/__init__.py
dravik/screens/charts.py
dravik/screens/error.py
dravik/screens/help.py
dravik/screens/quit.py
dravik/screens/refresh.py
dravik/screens/reports.py
dravik/screens/transactions.py
dravik/styles/account_details.tcss
dravik/styles/charts.tcss
dravik/styles/error.tcss
dravik/styles/help.tcss
dravik/styles/main.tcss
dravik/styles/quit.tcss
dravik/styles/refresh.tcss
dravik/styles/reports.tcss
dravik/styles/transaction_details.tcss
dravik/styles/transactions.tcss
dravik-0.24.dist-info/METADATA
dravik-0.24.dist-info/WHEEL
dravik-0.24.dist-info/entry_points.txt
dravik-0.24.dist-info/licenses/LICENSE
dravik-0.24.dist-info/RECORD
