Metadata-Version: 2.4
Name: dravik
Version: 0.24
Summary: Hledger TUI
Project-URL: Source, https://github.com/Yaser-Amiri/dravik
Author-email: Yaser Amiri <yaser.amiri95@gmail.com>
License:                     GNU GENERAL PUBLIC LICENSE
License-File: LICENSE
Keywords: UV,accounting,cli,hledger,python,python3,terminal,textual,tui
Classifier: Development Status :: 4 - Beta
Classifier: Environment :: Console
Classifier: License :: OSI Approved :: GNU General Public License v3 (GPLv3)
Classifier: Natural Language :: English
Classifier: Operating System :: POSIX :: Linux
Classifier: Programming Language :: Python :: 3 :: Only
Classifier: Programming Language :: Python :: 3.13
Classifier: Topic :: Office/Business :: Financial :: Accounting
Classifier: Topic :: Software Development :: Libraries :: Python Modules
Classifier: Topic :: Terminals
Classifier: Typing :: Typed
Requires-Python: >=3.13
Requires-Dist: pydantic==2.11.7
Requires-Dist: textual-plotext==1.0.1
Requires-Dist: textual==5.0.1
